Workbook

Sheet Catálogo
A1: Cervecería Bruma — Catálogo de productos
A2: Cerveza artesanal del sur de Chile · Valdivia, Región de Los Ríos · Venta exclusiva para mayores de 18 años
A3: Precios en pesos chilenos (CLP), IVA incluido. Fuente: catálogo del sitio web (js/productos.js).
A5: Código | B5: Producto | C5: Estilo | D5: Categoría | E5: ABV (%) | F5: IBU | G5: Presentación | H5: Volumen (ml) | I5: Precio (CLP) | J5: Precio por litro (CLP) | K5: Descripción
A6: BRU001 | B6: Bruma Costera | C6: Pale Ale | D6: Ale | E6: 5.2 | F6: 32 | G6: Botella 330 ml | H6: 330 | I6: 5990 | J6: =ROUND(I6/H6*1000,0) -> 18152 | K6: Pale Ale ligera con notas cítricas de lúpulo Cascade y final seco, pensada para el atardecer frente al mar.
A7: BRU002 | B7: Niebla Negra | C7: Stout | D7: Stout | E7: 6.8 | F7: 40 | G7: Botella 330 ml | H7: 330 | I7: 6490 | J7: =ROUND(I7/H7*1000,0) -> 19667 | K7: Stout cremosa con café tostado y cacao amargo, madurada en barrica. La favorita de las noches de lluvia.
A8: BRU003 | B8: Volcánica IPA | C8: IPA | D8: IPA | E8: 7.1 | F8: 61 | G8: Botella 330 ml | H8: 330 | I8: 6990 | J8: =ROUND(I8/H8*1000,0) -> 21182 | K8: India Pale Ale intensa en lúpulo, con aromas a pino y fruta tropical. Amargor firme y memorable.
A9: BRU004 | B9: Rubia del Lago | C9: Lager | D9: Lager | E9: 4.6 | F9: 18 | G9: Botella 330 ml | H9: 330 | I9: 5490 | J9: =ROUND(I9/H9*1000,0) -> 16636 | K9: Lager dorada, liviana y refrescante, fermentada en frío durante seis semanas para máxima limpieza.
A10: BRU005 | B10: Ámbar de Turbera | C10: Amber Ale | D10: Ale | E10: 5.6 | F10: 28 | G10: Botella 330 ml | H10: 330 | I10: 6190 | J10: =ROUND(I10/H10*1000,0) -> 18758 | K10: Ale ámbar con maltas caramelo y un leve toque ahumado que recuerda a las turberas del sur.
A11: BRU006 | B11: Doble Lúpulo | C11: Double IPA | D11: IPA | E11: 8.4 | F11: 74 | G11: Botella 330 ml | H11: 330 | I11: 7490 | J11: =ROUND(I11/H11*1000,0) -> 22697 | K11: Double IPA robusta con dry-hopping triple de variedades del hemisferio sur, para paladares que buscan intensidad.
A12: BRU007 | B12: Trigo del Estuario | C12: Witbier | D12: Trigo | E12: 4.9 | F12: 14 | G12: Botella 330 ml | H12: 330 | I12: 5790 | J12: =ROUND(I12/H12*1000,0) -> 17545 | K12: Cerveza de trigo turbia con cáscara de naranja y cilantro. Suave, especiada y muy fácil de beber.
A13: BRU008 | B13: Imperial de Roble | C13: Imperial Stout | D13: Stout | E13: 9.5 | F13: 55 | G13: Botella 500 ml | H13: 500 | I13: 8990 | J13: =ROUND(I13/H13*1000,0) -> 17980 | K13: Imperial Stout envejecida en barricas de roble ex-whisky. Edición limitada de temporada fría.
A15: Nota: "Precio por litro" se calcula con fórmula (Precio ÷ Volumen × 1000) para comparar presentaciones de 330 ml y 500 ml.

Sheet Resumen
A1: Resumen del catálogo
A2: Todas las cifras se calculan con fórmulas a partir de la hoja "Catálogo".
A4: Indicadores generales
A5: Total de productos | B5: =COUNTA(Catálogo!$A$6:$A$13) -> 8
A6: Precio promedio (CLP) | B6: =ROUND(AVERAGE(Catálogo!$I$6:$I$13),0) -> 6678
A7: Precio mínimo (CLP) | B7: =MIN(Catálogo!$I$6:$I$13) -> 5490
A8: Precio máximo (CLP) | B8: =MAX(Catálogo!$I$6:$I$13) -> 8990
A9: Graduación alcohólica promedio (% ABV) | B9: =AVERAGE(Catálogo!$E$6:$E$13) -> 6.5125
A10: Amargor promedio (IBU) | B10: =ROUND(AVERAGE(Catálogo!$F$6:$F$13),0) -> 40
A11: Producto más caro | B11: =INDEX(Catálogo!$B$6:$B$13,MATCH(B8,Catálogo!$I$6:$I$13,0)) -> Imperial de Roble
A12: Producto más económico | B12: =INDEX(Catálogo!$B$6:$B$13,MATCH(B7,Catálogo!$I$6:$I$13,0)) -> Rubia del Lago
A14: Productos por categoría
A15: Categoría | B15: N° de productos | C15: Precio promedio (CLP) | D15: % del catálogo
A16: Ale | B16: =COUNTIF(Catálogo!$D$6:$D$13,A16) -> 2 | C16: =ROUND(AVERAGEIF(Catálogo!$D$6:$D$13,A16,Catálogo!$I$6:$I$13),0) -> 6090 | D16: =B16/$B$5 -> 0.25
A17: IPA | B17: =COUNTIF(Catálogo!$D$6:$D$13,A17) -> 2 | C17: =ROUND(AVERAGEIF(Catálogo!$D$6:$D$13,A17,Catálogo!$I$6:$I$13),0) -> 7240 | D17: =B17/$B$5 -> 0.25
A18: Lager | B18: =COUNTIF(Catálogo!$D$6:$D$13,A18) -> 1 | C18: =ROUND(AVERAGEIF(Catálogo!$D$6:$D$13,A18,Catálogo!$I$6:$I$13),0) -> 5490 | D18: =B18/$B$5 -> 0.125
A19: Stout | B19: =COUNTIF(Catálogo!$D$6:$D$13,A19) -> 2 | C19: =ROUND(AVERAGEIF(Catálogo!$D$6:$D$13,A19,Catálogo!$I$6:$I$13),0) -> 7740 | D19: =B19/$B$5 -> 0.25
A20: Trigo | B20: =COUNTIF(Catálogo!$D$6:$D$13,A20) -> 1 | C20: =ROUND(AVERAGEIF(Catálogo!$D$6:$D$13,A20,Catálogo!$I$6:$I$13),0) -> 5790 | D20: =B20/$B$5 -> 0.125
A21: Total | B21: =SUM(B16:B20) -> 8 | D21: =SUM(D16:D20) -> 1
A23: Condiciones de despacho
A24: Despacho gratis desde (CLP) | B24: 30000
A25: Costo de despacho bajo ese monto (CLP) | B25: 3500
A26: Origen: regla del carrito del sitio web (js/carrito.js). Las celdas azules sobre fondo amarillo son datos ingresados; si cambia la regla en el sitio, actualícelas aquí.
